panorama_sidekick/__init__.py
panorama_sidekick/cli.py
panorama_sidekick/devicegroup.py
panorama_sidekick/firewall.py
panorama_sidekick/panorama.py
panorama_sidekick/show.py
panorama_sidekick-0.1.3.dist-info/LICENSE
panorama_sidekick-0.1.3.dist-info/METADATA
panorama_sidekick-0.1.3.dist-info/WHEEL
panorama_sidekick-0.1.3.dist-info/entry_points.txt
panorama_sidekick-0.1.3.dist-info/RECORD
